{
  "头骨": "skull",
  "脊椎": "spine",
  "肋骨": "rib",
  "骨盆": "pelvis",
  "肩胛骨": "scapula",
  "锁骨": "clavicle",
  "髋骨": "hipBone",
  "腕骨": "carpal",
  "踝骨": "ankleBone",
  "跟腱": "achillesTendon",
  "韧带": "ligament",
  "软骨": "cartilage",
  "椎间盘": "intervertebralDisc",
  "半月板": "meniscus",
  "筋膜": "fascia",
  "脂肪层": "fatLayer",
  "真皮层": "dermisLayer",
  "表皮层": "epidermisLayer",
  "毛囊": "hairFollicle",
  "汗腺": "sweatGland",
  "皮脂腺": "sebaceousGland",
  "淋巴结": "lymphNode",
  "甲状腺": "thyroidGland",
  "肾上腺": "adrenalGland",
  "脑垂体": "pituitaryGland",
  "海马体": "hippocampus",
  "小脑": "cerebellum",
  "脑干": "brainstem",
  "视网膜": "retina",
  "晶状体": "crystallineLens",
  "角膜": "cornea",
  "鼓膜": "tympanicMembrane",
  "耳蜗": "cochlea",
  "嗅球": "olfactoryBulb",
  "味蕾": "tasteBud",
  "神经末梢": "nerveEnding",
  "突触": "synapse",
  "髓鞘": "myelinSheath",
  "灰质": "grayMatter",
  "白质": "whiteMatter",
  "大脑皮层": "cerebralCortex",
  "额叶": "frontalLobe",
  "颞叶": "temporalLobe",
  "顶叶": "parietalLobe",
  "枕叶": "occipitalLobe",
  "杏仁核": "amygdala",
  "下丘脑": "hypothalamus",
  "胼胝体": "corpusCallosum",
  "血管": "bloodVessel",
  "动脉": "artery",
  "静脉": "vein",
  "毛细血管": "capillary",
  "血红蛋白": "hemoglobin",
  "白细胞": "whiteBloodCell",
  "红细胞": "redBloodCell",
  "血小板": "platelet",
  "骨髓": "boneMarrow",
  "横膈膜": "diaphragm",
  "食道": "esophagus",
  "十二指肠": "duodenum",
  "阑尾": "appendix",
  "膀胱": "bladder",
  "前列腺": "prostate",
  "子宫": "uterus",
  "输卵管": "fallopianTube",
  "视神经": "opticNerve",
  "坐骨神经": "sciaticNerve",
  "迷走神经": "vagusNerve",
  "三叉神经": "trigeminalNerve",
  "面部神经": "facialNerve",
  "尺骨": "ulna",
  "桡骨": "radius",
  "胫骨": "tibia",
  "腓骨": "fibula",
  "股骨": "femur",
  "髌骨": "patella",
  "胸骨": "sternum",
  "尾骨": "coccyx",
  "骶骨": "sacrum",
  "喉结": "adamApple",
  "声带": "vocalCord",
  "扁桃体": "tonsil",
  "胸腺": "thymus",
  "松果体": "pinealGland",

  "视觉": "vision",
  "听觉": "hearing",
  "嗅觉": "senseOfSmell",
  "味觉": "senseOfTaste",
  "触觉": "senseOfTouch",
  "痛觉": "senseOfPain",
  "温觉": "senseOfWarmth",
  "冷觉": "senseOfCold",
  "压觉": "senseOfPressure",
  "震动觉": "senseOfVibration",
  "平衡感": "senseOfBalance",
  "方向感": "senseOfDirection",
  "时间感": "senseOfTime",
  "空间感": "senseOfSpace",
  "距离感": "senseOfDistance",
  "立体感": "senseOfDepth",
  "色彩感": "senseOfColor",
  "节奏感": "senseOfRhythm",
  "韵律感": "senseOfCadence",
  "本体感觉": "proprioception",
  "内脏感觉": "visceralSensation",
  "皮肤感觉": "cutaneousSensation",
  "前庭觉": "vestibularSense",
  "光感": "lightSensitivity",
  "暗适应": "darkAdaptation",
  "色觉": "colorPerception",
  "深度知觉": "depthPerception",
  "运动知觉": "motionPerception",
  "听觉阈值": "hearingThreshold",
  "触觉灵敏度": "touchSensitivity",
  "温度感知": "temperaturePerception",
  "痛觉阈值": "painThreshold",
  "触觉适应": "touchAdaptation",
  "视觉适应": "visualAdaptation",
  "听觉过滤": "auditoryFiltering",
  "空间定位": "spatialOrientation",
  "运动感知": "kinestheticSense",
  "嗅觉灵敏度": "smellSensitivity",
  "味觉分辨": "tasteDiscrimination",

  "悲伤": "sadness",
  "忧郁": "melancholy",
  "沮丧": "frustration",
  "消沉": "depression",
  "颓废": "decadence",
  "绝望": "despair",
  "心碎": "heartbreak",
  "心酸": "bitterness",
  "委屈": "grievance",
  "冤枉": "wrongful",
  "苦闷": "gloom",
  "惆怅": "wistful",
  "迷茫": "bewilderment",
  "彷徨": "hesitation",
  "无助": "helplessness",
  "无力": "powerlessness",
  "无奈": "resignation",
  "妥协": "compromise",
  "顺从": "submission",
  "屈服": "yielding",
  "认命": "fatalism",
  "释然": "relief",
  "坦然": "calmAcceptance",
  "淡然": "indifference",
  "从容": "composure",
  "不安": "unease",
  "焦虑": "anxiety",
  "紧张": "nervousness",
  "恐惧": "fear",
  "害怕": "afraid",
  "胆怯": "timidity",
  "畏惧": "dread",
  "恐慌": "panic",
  "惊吓": "fright",
  "震惊": "shock",
  "惊恐": "terror",
  "嫉妒": "jealousy",
  "羡慕": "envy",
  "厌恶": "disgust",
  "反感": "aversion",
  "愤怒": "anger",
  "暴怒": "rage",
  "恼怒": "irritation",
  "烦躁": "agitation",
  "恼火": "annoyance",
  "愤恨": "resentment",
  "仇恨": "hatred",
  "怨恨": "grudge",
  "羞耻": "shame",
  "羞愧": "embarrassment",
  "内疚": "guilt",
  "悔恨": "regret",
  "惭愧": "shameful",
  "尴尬": "awkwardness",
  "孤独": "loneliness",
  "寂寞": "solitude",
  "空虚": "emptiness",
  "失落": "senseOfLoss",
  "思念": "longingFor",
  "怀念": "reminiscence",
  "眷恋": "attachment",
  "牵挂": "concern",
  "忐忑": "apprehension",
  "忐忑不安": "restless",
  "心烦意乱": "distracted",
  "心烦": "upset",
  "心痛": "aching",
  "心寒": "chilledHeart",
  "灰心": "disheartened",
  "寒心": "bitterlyDisappointed",
  "痛心": "grief",
  "伤心": "sorrow",
  "痛苦": "suffering",
  "折磨": "torment",
  "煎熬": "ordeal",
  "郁闷": "depressed",
  "憋闷": "stifled",
  "压抑": "suppressed",
  "沉重": "heaviness",
  "悲痛": "deepGrief",
  "哀伤": "mournful",
  "哀痛": "sorrowful",
  "悲凉": "desolate",
  "凄凉": "bleak",
  "苍凉": "dreary",
  "辛酸": "sadAndBitter",
  "苦涩": "bitter",
  "酸楚": "heartAche",

  "喜悦": "joy",
  "快乐": "happiness",
  "幸福": "wellbeing",
  "甜蜜": "sweetness",
  "温馨": "warmth",
  "感动": "touched",
  "温暖": "warmhearted",
  "希望": "hope",
  "憧憬": "longing",
  "期待": "anticipation",
  "向往": "aspiration",
  "渴望": "desire",
  "追求": "pursuit",
  "热情": "enthusiasm",
  "激情": "passion",
  "活力": "vitality",
  "朝气": "vigor",
  "生机": "vigor",
  "自信": "confidence",
  "自豪": "pride",
  "骄傲": "arrogance",
  "成就感": "senseOfAchievement",
  "满足感": "senseOfSatisfaction",
  "安全感": "senseOfSecurity",
  "归属感": "senseOfBelonging",
  "愉悦": "delight",
  "欣喜": "gladness",
  "庆幸": "rejoicing",
  "兴奋": "excitement",
  "激动": "thrilling",
  "振奋": "inspired",
  "鼓舞": "encouraged",
  "乐观": "optimism",
  "开朗": "cheerfulness",
  "豁达": "openmindedness",
  "释怀": "lettingGo",
  "舒畅": "relieved",
  "惬意": "contentment",
  "自在": "carefree",
  "安心": "peaceOfMind",
  "平静": "tranquility",
  "宁静": "serenity",
  "安详": "placid",
  "祥和": "harmonious",
  "和谐": "harmony",
  "感激": "gratitude",
  "感恩": "thankfulness",
  "欣慰": "gratified",
  "自豪感": "senseOfPride",
  "荣耀": "glory",
  "光荣": "honor",
  "尊贵": "nobility",
  "崇敬": "reverence",
  "敬畏": "awe",
  "赞叹": "admiration",
  "敬佩": "respect",
  "仰慕": "adoration",
  "钦佩": "esteem",
  "爱慕": "love",
  "爱意": "affection",
  "柔情": "tenderness",
  "温情": "warmheartedness",
  "深情": "deepAffection",
  "挚爱": "trueLove",
  "热爱": "ardentLove",
  "喜爱": "fondness",
  "喜欢": "liking",
  "中意": "preference",
  "心仪": "sweetheart",
  "痴迷": "obsession",
  "沉迷": "addiction",
  "陶醉": "intoxication",
  "沉醉": "enchantment",
  "着迷": "fascination",
  "倾心": "admiration",
  "心动": "heartFlutter",

  "勇敢": "bravery",
  "懦弱": "cowardice",
  "坚强": "strength",
  "脆弱": "fragility",
  "果断": "decisiveness",
  "犹豫": "hesitation",
  "谨慎": "caution",
  "鲁莽": "recklessness",
  "稳重": "steadiness",
  "浮躁": "impatience",
  "内敛": "reservedness",
  "外向": "extroversion",
  "含蓄": "subtlety",
  "直率": "frankness",
  "谦虚": "modesty",
  "自大": "conceit",
  "自卑": "inferiority",
  "独立": "independence",
  "依赖": "dependence",
  "宽容": "tolerance",
  "苛刻": "harshness",
  "大度": "magnanimity",
  "小气": "pettiness",
  "善良": "kindness",
  "邪恶": "evil",
  "正直": "integrity",
  "狡诈": "cunning",
  "诚实": "honesty",
  "虚伪": "hypocrisy",
  "忠诚": "loyalty",
  "背叛": "betrayal",
  "慷慨": "generosity",
  "吝啬": "miserliness",
  "冷酷": "coldHearted",
  "粗鲁": "rudeness",
  "礼貌": "politeness",
  "无礼": "impoliteness",
  "耐心": "patience",
  "急躁": "impetuosity",
  "专注": "focus",
  "分心": "distraction",
  "自律": "selfDiscipline",
  "放纵": "indulgence",
  "勤奋": "diligence",
  "懒惰": "laziness",
  "节俭": "frugality",
  "浪费": "extravagance",
  "积极": "positivity",
  "消极": "negativity",
  "进取": "enterprising",
  "保守": "conservatism",
  "开放": "openness",
  "封闭": "closedness",
  "包容": "inclusiveness",
  "固执": "stubbornness",
  "变通": "flexibility",
  "随性": "spontaneity",
  "认真": "seriousness",
  "马虎": "carelessness",
  "仔细": "meticulousness",
  "粗心": "negligence",
  "细致": "thoroughness",
  "粗糙": "coarseness",
  "精致": "refinement",
  "朴素": "simplicity",
  "奢华": "luxury",
  "淡泊": "indifferenceToGain",
  "名利": "fameAndWealth",
  "知足": "contentment",
  "贪心": "greed",
  "无私": "selflessness",
  "自私": "selfishness",
  "公正": "fairness",
  "偏见": "bias",
  "公平": "impartiality",
  "正义": "justice",
  "仁慈": "mercy",
  "残忍": "cruelty",
  "同情": "sympathy",
  "冷漠": "indifference",
  "悲悯": "compassion",
  "怜悯": "pity",
  "温柔": "gentleness",
  "暴躁": "irascibility",
  "沉稳": "calmness",
  "安静": "quietness",
  "沉默": "silence",
  "幽默": "humor",
  "风趣": "wit",
  "机智": "cleverness",
  "愚蠢": "foolishness",
  "聪明": "intelligence",
  "睿智": "wisdom",
  "才智": "talent",
  "才华": "giftedness",
  "平庸": "mediocrity",
  "卓越": "excellence",
  "平凡": "ordinariness",
  "伟大": "greatness",
  "渺小": "insignificance",
  "卑微": "humility",
  "尊严": "dignity",
  "耻辱": "disgrace",
  "自尊": "selfRespect",
  "自爱": "selfLove",
  "自重": "selfRegard",

  "寒暄": "smallTalk",
  "问候": "greeting",
  "致谢": "appreciation",
  "道歉": "apology",
  "原谅": "forgiveness",
  "宽恕": "pardon",
  "赞美": "praise",
  "夸奖": "compliment",
  "鼓励": "encouragement",
  "安慰": "consolation",
  "支持": "support",
  "帮助": "help",
  "合作": "cooperation",
  "竞争": "competition",
  "谈判": "negotiation",
  "协商": "consultation",
  "沟通": "communication",
  "交流": "exchange",
  "分享": "sharing",
  "倾诉": "confiding",
  "倾听": "listening",
  "陪伴": "companionship",
  "关怀": "caring",
  "照顾": "care",
  "体贴": "consideration",
  "关心": "concern",
  "担忧": "worry",
  "牵挂": "thoughtfulness",
  "邀请": "invitation",
  "欢迎": "welcome",
  "欢送": "farewell",
  "告别": "parting",
  "重逢": "reunion",
  "聚餐": "dinnerGathering",
  "聚会": "gathering",
  "派对": "party",
  "庆祝": "celebration",
  "祝福": "blessing",
  "祝贺": "congratulation",
  "感谢": "gratefulness",
  "答谢": "acknowledgment",
  "回礼": "returnGift",
  "请客": "treating",
  "买单": "payingBill",
  "AA制": "goDutch",
  "社交": "socialization",
  "应酬": "socialEngagement",
  "人脉": "networking",
  "面子": "face",
  "人情": "favor",
  "关系": "relationship",
  "交情": "friendship",
  "友情": "friendship",
  "亲情": "familialLove",
  "爱情": "romanticLove",
  "恋情": "romance",
  "暗恋": "secretCrush",
  "表白": "confession",
  "分手": "breakup",
  "复合": "reconciliation",
  "冷战": "coldWar",
  "争吵": "argument",
  "和解": "settlement",
  "调解": "mediation",
  "仲裁": "arbitration",
  "让步": "concession",
  "僵局": "deadlock",
  "对峙": "confrontation",
  "冲突": "conflict",
  "矛盾": "contradiction",
  "误解": "misunderstanding",
  "澄清": "clarification",
  "解释": "explanation",
  "辩解": "defense",
  "争论": "debate",
  "议论": "discussion",
  "批评": "criticism",
  "指责": "accusation",
  "抱怨": "complaint",
  "诉苦": "complaining",
  "发牢骚": "grumbling",
  "吐槽": "roasting",
  "调侃": "teasing",
  "讽刺": "sarcasm",
  "挖苦": "mockery",
  "嘲笑": "ridicule",
  "嘲讽": "derision",
  "戏谑": "banter",
  "打趣": "jesting",
  "诙谐": "wittiness",
  "逗乐": "amusement",
  "取悦": "pleasing",
  "讨好": "currying",
  "巴结": "flattery",
  "奉承": "fawning",
  "谄媚": "ingratiation",
  "拍马屁": "sycophancy",
  "敷衍": "perfunctory",
  "搪塞": "evasion",
  "回避": "avoidance",
  "无视": "disregard",
  "忽视": "neglect",
  "冷落": "coldShoulder",
  "孤立": "isolation",
  "排挤": "exclusion",
  "排斥": "rejection",
  "接纳": "acceptance",
  "理解": "understanding",
  "体谅": "empathy",
  "友善": "friendliness",
  "和善": "goodWill",
  "亲切": "cordial",
  "待客": "hospitality",
  "做客": "visiting",
  "串门": "droppingBy",
  "拜访": "callingOn",
  "探望": "visitingSick",
  "慰问": "consolation",
  "吊唁": "condolence",

  "信任": "trust",
  "猜疑": "suspicion",
  "怀疑": "doubt",
  "真诚": "sincerity",
  "伪装": "disguise",
  "掩饰": "concealment",
  "坦诚": "candor",
  "默契": "tacitUnderstanding",
  "隔阂": "estrangement",
  "疏远": "alienation",
  "亲近": "closeness",
  "亲密": "intimacy",
  "界限": "boundary",
  "距离": "distance",
  "平等": "equality",
  "尊重": "respect",
  "客气": "politeness",
  "知己": "soulmate",
  "知音": "kindredSpirit",
  "伙伴": "partner",
  "搭档": "teammate",
  "同事": "colleague",
  "同学": "classmate",
  "战友": "comradeInArms",
  "邻居": "neighbor",
  "陌生人": "stranger",
  "熟人": "acquaintance",
  "亲朋好友": "friendsAndFamily",
  "亲戚": "relative",
  "家人": "family",
  "伴侣": "companion",
  "配偶": "spouse",
  "恋人": "lover",
  "情人": "sweetheart",
  "爱人": "beloved",
  "孩子": "child",
  "父母": "parents",
  "长辈": "elder",
  "晚辈": "youngerGeneration",
  "同辈": "peer",
  "兄弟": "brother",
  "姐妹": "sister",
  "闺蜜": "bestFriend",
  "铁哥们": "closeBuddy",
  "老板": "boss",
  "上司": "superior",
  "下属": "subordinate",
  "客户": "client",
  "供应商": "supplier",
  "合作伙伴": "businessPartner",
  "竞争者": "competitor",
  "盟友": "ally",
  "对手": "opponent",
  "敌人": "enemy",
  "路人": "passerby",
  "观众": "audience",
  "粉丝": "fan",
  "偶像": "idol",
  "导师": "mentor",
  "学徒": "apprentice",
  "前辈": "senior",
  "后辈": "junior",
  "权威": "authority",
  "平民": "commoner",
  "领袖": "leader",
  "追随者": "follower",
  "志愿者": "volunteer",
  "服务者": "server",
  "受益者": "beneficiary",
  "赞助者": "sponsor",
  "捐赠者": "donor",
  "受助者": "recipient",

  "微笑": "smile",
  "大笑": "laugh",
  "傻笑": "giggle",
  "苦笑": "bitterSmile",
  "冷笑": "sneer",
  "嘲笑": "mockingSmile",
  "坏笑": "smirk",
  "偷笑": "snicker",
  "抿嘴": "pursedLips",
  "撅嘴": "pouting",
  "嘟嘴": "puffingCheeks",
  "撇嘴": "curlingLip",
  "咬唇": "lipBiting",
  "吐舌": "tongueOut",
  "皱眉": "frowning",
  "挑眉": "raisedEyebrow",
  "瞪眼": "wideEyes",
  "眯眼": "squinting",
  "翻白眼": "eyeRoll",
  "斜视": "sideGlance",
  "凝视": "gaze",
  "注视": "stare",
  "扫视": "glance",
  "瞥见": "peek",
  "露齿笑": "grin",
  "哈哈大笑": "roar",
  "捧腹大笑": "bellyLaugh",
  "笑不露齿": "shySmile",
  "笑眯眯": "smilingEyes",
  "笑嘻嘻": "beaming",
  "笑呵呵": "chuckling",
  "皮笑肉不笑": "fakeSmile",
  "似笑非笑": "enigmaticSmile",
  "面无表情": "pokerFace",
  "表情严肃": "sternExpression",
  "表情凝重": "graveExpression",
  "表情痛苦": "painfulExpression",
  "表情惊喜": "surprisedExpression",
  "表情惊讶": "astonishedExpression",
  "表情疑惑": "confusedExpression",
  "表情愤怒": "angryExpression",
  "表情冷漠": "indifferentExpression",
  "表情尴尬": "awkwardExpression",
  "表情紧张": "nervousExpression",
  "表情放松": "relaxedExpression",
  "表情专注": "focusedExpression",
  "表情兴奋": "excitedExpression",
  "表情沮丧": "dejectedExpression",
  "表情得意": "smugExpression",
  "表情惭愧": "ashamedExpression",
  "表情自信": "confidentExpression",
  "表情满足": "satisfiedExpression",
  "表情不安": "uneasyExpression",
  "挤眉弄眼": "winking",
  "眉开眼笑": "beamingFace",
  "眉飞色舞": "radiantFace",
  "愁眉苦脸": "worriedFace",
  "愁眉不展": "knittedBrows",
  "横眉竖眼": "glaringFace",
  "慈眉善目": "gentleExpression",
  "贼眉鼠眼": "shiftyEyes",
  "挤眼": "wink",
  "闭眼": "closedEyes",
  "眨眼": "blink",
  "瞪大眼睛": "wideOpenEyes",
  "怒目圆睁": "fierceStare",
  "目瞪口呆": "dumbfounded",
  "瞠目结舌": "astonished",
  "垂头丧气": "dejected",
  "昂首挺胸": "headHigh",

  "点头": "nod",
  "摇头": "headShake",
  "耸肩": "shrug",
  "摊手": "palmUp",
  "抱胸": "crossedArms",
  "叉腰": "handsOnHips",
  "踮脚": "tiptoe",
  "弯腰": "bending",
  "鞠躬": "bow",
  "拥抱": "hug",
  "牵手": "handHolding",
  "挽手": "armLinking",
  "勾肩搭背": "armAroundShoulder",
  "推搡": "shoving",
  "拍肩": "shoulderTap",
  "拍背": "backPat",
  "指指点点": "pointing",
  "挥手": "waving",
  "招手": "beckoning",
  "竖大拇指": "thumbsUp",
  "比心": "heartGesture",
  "握拳": "clenchedFist",
  "击掌": "highFive",
  "鼓掌": "clapping",
  "拍手": "handClapping",
  "搓手": "handRubbing",
  "摆手": "handWaving",
  "挥手告别": "wavingGoodbye",
  "双手合十": "prayerHands",
  "抱拳": "fistPalm",
  "拱手": "cuppedFist",
  "作揖": "bowingGesture",
  "下跪": "kneeling",
  "磕头": "kowtowing",
  "踢腿": "kicking",
  "跺脚": "footStamping",
  "跳脚": "jumping",
  "原地踏步": "marchingInPlace",
  "手舞足蹈": "dancingGestures",
  "张牙舞爪": "clawingGestures",
  "摩拳擦掌": "eagerForAction",
  "挽袖子": "rollingUpSleeves",
  "伸懒腰": "stretching",
  "打哈欠": "yawning",
  "打喷嚏": "sneezing",
  "咳嗽": "coughing",
  "吞咽": "swallowing",
  "深呼吸": "deepBreathing",
  "叹气": "sighing",
  "喘气": "panting",
  "抽泣": "sobbing",
  "哭泣": "crying",
  "流泪": "tearing",
  "擦眼泪": "wipingTears",
  "擤鼻涕": "blowingNose",
  "捂嘴": "coveringMouth",
  "捂脸": "coveringFace",
  "摸头": "headTouch",
  "挠头": "headScratch",
  "揪头发": "hairPulling",
  "扯衣角": "tuggingClothes",
  "抓耳挠腮": "fidgeting",
  "坐立不安": "restless",
  "手忙脚乱": "flustered",
  "小心翼翼": "cautiousMovement",
  "蹑手蹑脚": "tiptoeing",
  "大摇大摆": "strutting",
  "昂首阔步": "striding",
  "连蹦带跳": "skipping",
  "慢条斯理": "unhurried",
  "风风火火": "hurried",
  "雷厉风行": "decisiveAction",
  "懒洋洋": "languid",
  "无精打采": "listless",
  "精神抖擞": "energetic",
  "容光焕发": "glowing",
  "面红耳赤": "blushing",
  "脸色苍白": "paleFace",
  "大汗淋漓": "sweating",
  "瑟瑟发抖": "trembling",
  "战战兢兢": "quivering",
  "浑身发抖": "shivering",
  "咬牙切齿": "gnashingTeeth",
  "跃跃欲试": "eagerToTry",

  "程序员": "programmer",
  "设计师": "designer",
  "产品经理": "productManager",
  "项目经理": "projectManager",
  "测试工程师": "testEngineer",
  "运维工程师": "operationsEngineer",
  "架构师": "architect",
  "数据分析师": "dataAnalyst",
  "算法工程师": "algorithmEngineer",
  "前端工程师": "frontendEngineer",
  "后端工程师": "backendEngineer",
  "全栈工程师": "fullstackEngineer",
  "技术总监": "techDirector",
  "主管": "supervisor",
  "经理": "manager",
  "总监": "director",
  "副总裁": "vicePresident",
  "总裁": "president",
  "创始人": "founder",
  "联合创始人": "coFounder",
  "股东": "shareholder",
  "投资人": "investor",
  "创业者": "entrepreneur",
  "自由职业者": "freelancer",
  "咨询顾问": "consultant",
  "培训师": "trainer",
  "讲师": "lecturer",
  "教授": "professor",
  "研究员": "researcher",
  "科学家": "scientist",
  "医生": "doctor",
  "护士": "nurse",
  "药剂师": "pharmacist",
  "律师": "lawyer",
  "法官": "judge",
  "警察": "policeOfficer",
  "消防员": "firefighter",
  "军人": "soldier",
  "记者": "journalist",
  "编辑": "editor",
  "作家": "writer",
  "画家": "painter",
  "音乐家": "musician",
  "演员": "actor",
  "摄影师": "photographer",
  "厨师": "chef",
  "面包师": "baker",
  "理发师": "hairdresser",
  "司机": "driver",
  "飞行员": "pilot",
  "船员": "crew",
  "快递员": "deliveryPerson",
  "邮递员": "mailman",
  "清洁工": "cleaner",
  "保安": "securityGuard",
  "门卫": "doorman",
  "管家": "butler",
  "保姆": "nanny",
  "园丁": "gardener",
  "工程师": "engineer",
  "技术员": "technician",
  "工人": "worker",
  "农民": "farmer",
  "渔民": "fisherman",
  "猎人": "hunter",
  "牧民": "herdsman",
  "商人": "merchant",
  "店主": "shopkeeper",
  "服务员": "waiter",
  "收银员": "cashier",
  "销售员": "salesperson",
  "客服": "customerService",
  "会计": "accountant",
  "审计": "auditor",
  "秘书": "secretary",
  "翻译": "translator",
  "导游": "tourGuide",
  "健身教练": "fitnessTrainer",
  "瑜伽教练": "yogaInstructor",
  "心理咨询师": "psychologist",
  "社工": "socialWorker",
  "退休人员": "retiree",
  "学生": "student",
  "实习生": "intern",
  "大师": "master",
  "专家": "expert",
  "学者": "scholar",
  "学霸": "topStudent",
  "天才": "genius",
  "精英": "elite",
  "高手": "ace",
  "新手": "newbie",
  "老手": "veteran",
  "骨干": "backbone",
  "接班人": "successor",
  "领导者": "leadership",
  "决策者": "decisionMaker",
  "执行者": "executor",
  "管理者": "administrator",
  "监督者": "monitor",
  "协调者": "coordinator",
  "组织者": "organizer",
  "发起者": "initiator",
  "参与者": "participant",
  "旁观者": "bystander",
  "见证人": "witness",
  "继承人": "heir",
  "候选人": "candidate",
  "挑战者": "challenger",
  "胜利者": "victor",
  "失败者": "loser",
  "受害者": "victim",
  "幸存者": "survivor",
  "英雄": "hero",
  "反派": "villain",
  "叛徒": "traitor",
  "间谍": "spy",
  "侦探": "detective",
  "陪审员": "juror",
  "被告": "defendant",
  "原告": "plaintiff",
  "辩护人": "defender",
  "调解员": "mediator",

  "思考": "thinking",
  "沉思": "contemplation",
  "反思": "reflection",
  "回忆": "reminiscence",
  "想象": "imagination",
  "联想": "association",
  "猜测": "speculation",
  "判断": "judgment",
  "推理": "reasoning",
  "分析": "analysis",
  "归纳": "induction",
  "总结": "summary",
  "比较": "comparison",
  "权衡": "weighing",
  "抉择": "choice",
  "决定": "decision",
  "纠结": "innerConflict",
  "怀疑": "questioning",
  "确认": "confirmation",
  "肯定": "affirmation",
  "否定": "negation",
  "接受": "acceptance",
  "拒绝": "rejection",
  "顿悟": "epiphany",
  "灵感": "inspiration",
  "创意": "creativity",
  "直觉": "intuition",
  "预感": "premonition",
  "警觉": "alertness",
  "警惕": "vigilance",
  "清醒": "sobriety",
  "糊涂": "confusion",
  "迷惑": "bewilderment",
  "困惑": "puzzlement",
  "好奇": "curiosity",
  "兴趣": "interest",
  "动力": "motivation",
  "意志": "willpower",
  "决心": "determination",
  "毅力": "perseverance",
  "恒心": "constancy",
  "信心": "faith",
  "信念": "belief",
  "理想": "ideal",
  "目标": "goal",
  "计划": "plan",
  "策略": "strategy",
  "战术": "tactics",
  "谋略": "stratagem",
  "智慧": "wisdom",
  "知识": "knowledge",
  "经验": "experience",
  "教训": "lesson",
  "领悟": "comprehension",
  "认识": "cognition",
  "感知": "perception",
  "觉察": "awareness",
  "意识": "consciousness",
  "潜意识": "subconscious",
  "记忆": "memory",
  "遗忘": "forgetting",
  "冥想": "meditation",
  "注意": "attention",
  "忽略": "neglect",
  "觉醒": "awakening",
  "开悟": "enlightenment",
  "觉悟": "realization",
  "明悟": "clarity",
  "彻悟": "thoroughUnderstanding",
  "醒悟": "comingToRealize",
  "感悟": "insight",
  "体悟": "personalUnderstanding",
  "参悟": "contemplativeInsight",
  "洞察": "penetration",
  "远见": "foresight",
  "洞悉": "perceive",
  "预见": "prediction",
  "预判": "anticipation",
  "推断": "inference",
  "推论": "deduction",
  "论证": "argumentation",
  "假设": "hypothesis",
  "验证": "verification",
  "证实": "corroboration",
  "反驳": "refutation",
  "质疑": "questioning",
  "批判": "criticism",
  "审视": "scrutiny",
  "评估": "evaluation",
  "衡量": "measurement",
  "斟酌": "deliberation",
  "酝酿": "brewing",
  "沉淀": "sedimentation",
  "升华": "sublimation",
  "蜕变": "metamorphosis",
  "重生": "rebirth",

  "悲观": "pessimism",
  "平和": "peaceful",
  "淡定": "composed",
  "从容不迫": "unflappable",
  "心平气和": "calm",
  "泰然自若": "selfPossessed",
  "宠辱不惊": "unfazed",
  "不卑不亢": "neitherArrogantNorHumble",
  "随遇而安": "contentWithAnySituation",
  "知足常乐": "contentAndHappy",
  "自强不息": "ceaselessStriving",
  "厚德载物": "virtuous",
  "虚怀若谷": "humble",
  "海纳百川": "tolerant",
  "与人为善": "benevolent",
  "助人为乐": "helpful",
  "见义勇为": "courageous",
  "舍己为人": "selfless",
  "大公无私": "impartial",
  "先人后己": "altruistic",
  "克己奉公": "disciplined",
  "清正廉洁": "incorruptible",
  "两袖清风": "cleanHands",
  "一尘不染": "spotless",
  "洁身自好": "moral",
  "严于律己": "strictWithSelf",
  "宽以待人": "tolerantOfOthers",
  "推己及人": "empathetic",
  "设身处地": "puttingOneselfInOthersShoes",
  "换位思考": "perspectiveTaking",
  "将心比心": "empathizing",
  "有教养": "wellBred",
  "有礼貌": "courteous",
  "有修养": "cultured",
  "有气质": "elegant",
  "有风度": "graceful",
  "有涵养": "refined",
  "有品味": "tasteful",
  "有格调": "stylish",
  "有内涵": "substantive",
  "有深度": "profound",
  "有思想": "thoughtful",
  "有见解": "insightful",
  "有远见": "farsighted",
  "有担当": "responsible",
  "有魄力": "bold",
  "有魅力": "charismatic",
  "有才华": "gifted",
  "有能力": "capable",
  "有潜力": "potential",
  "有前途": "promising",
  "有理想": "idealistic",
  "有抱负": "ambitious",
  "有目标": "goalOriented",
  "有动力": "motivated",
  "有热情": "enthusiastic",
  "有干劲": "energetic",
  "有活力": "vibrant",
  "有朝气": "youthful",
  "有生机": "thriving",
  "有未来": "futureOriented",
  "坚韧": "resilient",
  "柔弱": "tender",
  "刚强": "tough",
  "温和": "mild",
  "激烈": "intense",
  "暴烈": "violent",
  "和蔼": "gentle",
  "冷淡": "cold",
  "温暖": "warm",
  "热情洋溢": "exuberant",
  "深沉": "profound",
  "浅薄": "superficial",
  "宽厚": "generous",
  "刻薄": "mean",
  "圆滑": "smooth",
  "耿直": "straightforward",
  "世故": "worldly",
  "天真": "naive",
  "老练": "seasoned",
  "成熟": "mature",
  "幼稚": "childish",
  "稳健": "steady",
  "轻浮": "frivolous",
  "庄重": "solemn",
  "严肃": "serious",
  "爽朗": "brightAndCheerful",
  "阴沉": "gloomy",
  "坦率": "frank",
  "阴险": "sinister",
  "坦荡": "magnanimous",
  "小肚鸡肠": "petty",
  "豁达大度": "broadMinded",
  "心胸狭窄": "narrowMinded",
  "光明磊落": "openAndAboveboard",
  "阴险狡诈": "treacherous",
  "心地善良": "kindHearted",
  "铁石心肠": "hardHearted",
  "善解人意": "understanding",
  "多愁善感": "sentimental",
  "冷若冰霜": "icy",
  "热情似火": "fiery",
  "淡泊名利": "detached",
  "争强好胜": "competitive",
  "与世无争": "peaceful",
  "随波逐流": "conformist",
  "特立独行": "maverick",
  "标新立异": "innovative",
  "循规蹈矩": "conventional",
  "墨守成规": "traditional",
  "破旧立新": "revolutionary",
  "推陈出新": "modernizing",
  "守旧": "conservative",
  "激进": "radical",
  "中庸": "moderate",
  "极端": "extreme",
  "折中": "compromising",
  "偏激": "biased",
  "公正无私": "impartial",
  "刚正不阿": "upright",
  "阿谀奉承": "sycophantic",
  "正直无私": "selfless",
  "贪得无厌": "greedy",
  "见利忘义": "mercenary",
  "仗义疏财": "generous",
  "惜财如命": "miserly",
  "勤俭节约": "thrifty",
  "挥金如土": "extravagant",
  "勤勤恳恳": "hardworking",
  "好吃懒做": "lazy",
  "任劳任怨": "uncomplaining",
  "拈轻怕重": "shirking",
  "废寝忘食": "dedicated",
  "三心二意": "halfhearted",
  "一心一意": "wholehearted",
  "全心全意": "devoted",
  "心不在焉": "absentminded",
  "聚精会神": "attentive",
  "专心致志": "concentrated",
  "敷衍了事": "perfunctory",
  "一丝不苟": "meticulous",
  "粗枝大叶": "sloppy",
  "谨小慎微": "overcautious",
  "胆大心细": "boldAndCareful",
  "胆大妄为": "reckless",
  "缩手缩脚": "timid",
  "大刀阔斧": "bold",
  "雷厉风行": "swift",
  "优柔寡断": "indecisive",
  "当机立断": "decisive",
  "犹豫不决": "vacillating",
  "果敢": "courageous",
  "果决": "resolute",
  "坚韧不拔": "persevering",
  "百折不挠": "tenacious",
  "知难而进": "enterprising",
  "知难而退": "retreating",
  "迎难而上": "facing",
  "半途而废": "quitting",
  "坚持不懈": "persistent",
  "持之以恒": "constant",
  "一曝十寒": "inconsistent",
  "始终如一": "consistent",
  "善始善终": "thorough",
  "有始无终": "incomplete",
  "见异思迁": "fickle",
  "矢志不渝": "steadfast",
  "忠心耿耿": "loyal",
  "朝三暮四": "changeable",
  "唯利是图": "opportunist",
  "两面三刀": "duplicitous",
  "口是心非": "insincere",
  "表里如一": "consistent",
  "光明正大": "upright",
  "阴奉阳违": "deceptive",
  "心直口快": "straightforward",
  "拐弯抹角": "indirect",
  "直言不讳": "candid",
  "含糊其辞": "vague",
  "斩钉截铁": "categorical",
  "模棱两可": "ambiguous",
  "坚定不移": "firm",
  "摇摆不定": "wavering",
  "立场坚定": "resolute",
  "见风使舵": "opportunist",
  "随声附和": "agreeable",
  "固执己见": "stubborn",
  "从善如流": "open",
  "兼听则明": "openMinded",
  "偏信则暗": "biased",
  "博采众长": "eclectic",
  "刚愎自用": "selfOpinionated",
  "虚心好学": "studious",
  "骄傲自满": "complacent",
  "不耻下问": "humble",
  "好为人师": "condescending",
  "学无止境": "lifelongLearning",
  "浅尝辄止": "superficial",
  "精益求精": "excellence",
  "尽善尽美": "perfectionism",
  "得过且过": "slacking",
  "力求完美": "striving",
  "追求卓越": "excellence",
  "安于现状": "complacent",
  "锐意进取": "enterprising",
  "固步自封": "selfLimiting",
  "开拓创新": "innovative",
  "因循守旧": "backwardLooking"
}